LICENSE
MANIFEST.in
README.md
pyproject.toml
setup.py
vassar_arx_r5_sdk/__init__.py
vassar_arx_r5_sdk/build.sh
vassar_arx_r5_sdk/setup.sh
vassar_arx_r5_sdk/test_dual_arm.py
vassar_arx_r5_sdk/test_keyboard.py
vassar_arx_r5_sdk/test_kinematic_solver.py
vassar_arx_r5_sdk/test_single_arm.py
vassar_arx_r5_sdk.egg-info/PKG-INFO
vassar_arx_r5_sdk.egg-info/SOURCES.txt
vassar_arx_r5_sdk.egg-info/dependency_links.txt
vassar_arx_r5_sdk.egg-info/requires.txt
vassar_arx_r5_sdk.egg-info/top_level.txt
vassar_arx_r5_sdk/bimanual/CMakeLists.txt
vassar_arx_r5_sdk/bimanual/__init__.py
vassar_arx_r5_sdk/bimanual/build.sh
vassar_arx_r5_sdk/bimanual/api/kinematic_solver.hpp
vassar_arx_r5_sdk/bimanual/api/libkinematic_solver.so
vassar_arx_r5_sdk/bimanual/api/arx_hardware_interface/include/arx_hardware_interface/typedef/HybridJointTypeDef.hpp
vassar_arx_r5_sdk/bimanual/api/arx_r5_python/arx_r5_python.cpython-310-x86_64-linux-gnu.so
vassar_arx_r5_sdk/bimanual/api/arx_r5_python/kinematic_solver.cpython-310-x86_64-linux-gnu.so
vassar_arx_r5_sdk/bimanual/api/arx_r5_src/libarx_r5_src-arm64.so
vassar_arx_r5_sdk/bimanual/api/arx_r5_src/libarx_r5_src.so
vassar_arx_r5_sdk/bimanual/api/arx_r5_src/include/Eigen/src/Cholesky/LDLT.h
vassar_arx_r5_sdk/bimanual/api/arx_r5_src/include/Eigen/src/Cholesky/LLT.h
vassar_arx_r5_sdk/bimanual/api/arx_r5_src/include/Eigen/src/Cholesky/LLT_LAPACKE.h
vassar_arx_r5_sdk/bimanual/api/arx_r5_src/include/Eigen/src/CholmodSupport/CholmodSupport.h
vassar_arx_r5_sdk/bimanual/api/arx_r5_src/include/Eigen/src/Core/ArithmeticSequence.h
vassar_arx_r5_sdk/bimanual/api/arx_r5_src/include/Eigen/src/Core/Array.h
vassar_arx_r5_sdk/bimanual/api/arx_r5_src/include/Eigen/src/Core/ArrayBase.h
vassar_arx_r5_sdk/bimanual/api/arx_r5_src/include/Eigen/src/Core/ArrayWrapper.h
vassar_arx_r5_sdk/bimanual/api/arx_r5_src/include/Eigen/src/Core/Assign.h
vassar_arx_r5_sdk/bimanual/api/arx_r5_src/include/Eigen/src/Core/AssignEvaluator.h
vassar_arx_r5_sdk/bimanual/api/arx_r5_src/include/Eigen/src/Core/Assign_MKL.h
vassar_arx_r5_sdk/bimanual/api/arx_r5_src/include/Eigen/src/Core/BandMatrix.h
vassar_arx_r5_sdk/bimanual/api/arx_r5_src/include/Eigen/src/Core/Block.h
