Metadata-Version: 2.1
Name: vassar-arx-r5-sdk
Version: 0.2.2
Summary: Python SDK for ARX R5 Robot Arm Control
Home-page: https://github.com/ARXroboticsX/R5
Author: ARXrobotics
Author-email: ARXrobotics <contact@arx-x.com>
Maintainer: Vassar
License: BSD-3-Clause
Project-URL: Homepage, https://github.com/ARXroboticsX/R5
Project-URL: Bug Reports, https://github.com/ARXroboticsX/R5/issues
Project-URL: Source, https://github.com/ARXroboticsX/R5
Keywords: robotics,robot arm,ARX,R5,control
Requires-Python: >=3.10
Provides-Extra: dev
License-File: LICENSE
